{
  "$schema": "https://developer.microsoft.com/json-schemas/fabric/item/report/definition/visualContainer/2.4.0/schema.json",
  "name": "8bf00cb9e8502c6963dd",
  "position": {
    "x": 425.5408970976253,
    "y": 84.432717678100261,
    "z": 1000,
    "height": 369.25241864555846,
    "width": 843.20140721196128,
    "tabOrder": 0
  },
  "visual": {
    "visualType": "pivotTable",
    "query": {
      "queryState": {
        "Columns": {
          "projections": [
            {
              "field": {
                "Column": {
                  "Expression": {
                    "SourceRef": {
                      "Entity": "D_Calendario"
                    }
                  },
                  "Property": "Mes/Ano"
                }
              },
              "queryRef": "D_Calendario.Mes/Ano",
              "nativeQueryRef": "Mes/Ano",
              "active": true
            }
          ]
        },
        "Rows": {
          "projections": [
            {
              "field": {
                "Column": {
                  "Expression": {
                    "SourceRef": {
                      "Entity": "D_PlanoDeContas"
                    }
                  },
                  "Property": "DRE"
                }
              },
              "queryRef": "D_PlanoDeContas.DRE",
              "nativeQueryRef": "DRE",
              "active": true
            },
            {
              "field": {
                "Column": {
                  "Expression": {
                    "SourceRef": {
                      "Entity": "F_Movimentacoes"
                    }
                  },
                  "Property": "Nome_Operacao"
                }
              },
              "queryRef": "F_Movimentacoes.Nome_Operacao",
              "nativeQueryRef": "Nome_Operacao",
              "active": false
            },
            {
              "field": {
                "Column": {
                  "Expression": {
                    "SourceRef": {
                      "Entity": "F_Movimentacoes"
                    }
                  },
                  "Property": "Produto"
                }
              },
              "queryRef": "F_Movimentacoes.Produto",
              "nativeQueryRef": "Descricao",
              "active": false,
              "displayName": "Descricao"
            },
            {
              "field": {
                "Column": {
                  "Expression": {
                    "SourceRef": {
                      "Entity": "D_Calendario"
                    }
                  },
                  "Property": "Date"
                }
              },
              "queryRef": "D_Calendario.Date",
              "nativeQueryRef": "Date",
              "active": false
            }
          ]
        },
        "Values": {
          "projections": [
            {
              "field": {
                "Measure": {
                  "Expression": {
                    "SourceRef": {
                      "Entity": "Medidas_DRE"
                    }
                  },
                  "Property": "Valor_DRE"
                }
              },
              "queryRef": "Medidas.Valor_DRE",
              "nativeQueryRef": "Valor",
              "displayName": "Valor"
            },
            {
              "field": {
                "Measure": {
                  "Expression": {
                    "SourceRef": {
                      "Entity": "Medidas_DRE"
                    }
                  },
                  "Property": "% DRE"
                }
              },
              "queryRef": "Medidas.% DRE",
              "nativeQueryRef": "%",
              "displayName": "%"
            }
          ]
        }
      }
    },
    "expansionStates": [
      {
        "roles": [
          "Rows"
        ],
        "levels": [
          {
            "queryRefs": [
              "D_PlanoDeContas.DRE"
            ],
            "isCollapsed": true,
            "identityKeys": [
              {
                "Column": {
                  "Expression": {
                    "SourceRef": {
                      "Entity": "D_PlanoDeContas"
                    }
                  },
                  "Property": "DRE"
                }
              }
            ],
            "isPinned": true
          },
          {
            "queryRefs": [
              "F_Movimentacoes.Nome_Operacao"
            ],
            "isCollapsed": true,
            "identityKeys": [
              {
                "Column": {
                  "Expression": {
                    "SourceRef": {
                      "Entity": "F_Movimentacoes"
                    }
                  },
                  "Property": "Nome_Operacao"
                }
              }
            ],
            "isPinned": true
          },
          {
            "queryRefs": [
              "F_Movimentacoes.Produto"
            ],
            "isCollapsed": true,
            "identityKeys": [
              {
                "Column": {
                  "Expression": {
                    "SourceRef": {
                      "Entity": "F_Movimentacoes"
                    }
                  },
                  "Property": "Produto"
                }
              }
            ],
            "isPinned": true
          },
          {
            "queryRefs": [
              "D_Calendario.Date"
            ],
            "isCollapsed": true,
            "identityKeys": [
              {
                "Column": {
                  "Expression": {
                    "SourceRef": {
                      "Entity": "D_Calendario"
                    }
                  },
                  "Property": "Date"
                }
              }
            ],
            "isPinned": true
          }
        ],
        "root": {}
      }
    ],
    "objects": {
      "values": [
        {
          "properties": {},
          "selector": {
            "data": [
              {
                "dataViewWildcard": {
                  "matchingOption": 1
                }
              }
            ],
            "metadata": "Medidas.Valor_DRE"
          }
        },
        {
          "properties": {
            "backColor": {
              "solid": {
                "color": {
                  "expr": {
                    "Measure": {
                      "Expression": {
                        "SourceRef": {
                          "Entity": "Medidas_DRE"
                        }
                      },
                      "Property": "CorFundo"
                    }
                  }
                }
              }
            }
          },
          "selector": {
            "data": [
              {
                "dataViewWildcard": {
                  "matchingOption": 0
                }
              }
            ],
            "metadata": "Medidas.Valor_DRE"
          }
        },
        {
          "properties": {},
          "selector": {
            "data": [
              {
                "dataViewWildcard": {
                  "matchingOption": 1
                }
              }
            ],
            "metadata": "Medidas.% DRE"
          }
        },
        {
          "properties": {
            "backColor": {
              "solid": {
                "color": {
                  "expr": {
                    "Measure": {
                      "Expression": {
                        "SourceRef": {
                          "Entity": "Medidas_DRE"
                        }
                      },
                      "Property": "CorFundo"
                    }
                  }
                }
              }
            }
          },
          "selector": {
            "data": [
              {
                "dataViewWildcard": {
                  "matchingOption": 0
                }
              }
            ],
            "metadata": "Medidas.% DRE"
          }
        }
      ],
      "general": [
        {
          "properties": {
            "layout": {
              "expr": {
                "Literal": {
                  "Value": "'Compact'"
                }
              }
            }
          }
        }
      ],
      "columnHeaders": [
        {
          "properties": {
            "fontColor": {
              "solid": {
                "color": {
                  "expr": {
                    "ThemeDataColor": {
                      "ColorId": 1,
                      "Percent": 0
                    }
                  }
                }
              }
            }
          }
        }
      ],
      "rowHeaders": [
        {
          "properties": {
            "fontColor": {
              "solid": {
                "color": {
                  "expr": {
                    "ThemeDataColor": {
                      "ColorId": 1,
                      "Percent": 0
                    }
                  }
                }
              }
            }
          }
        }
      ]
    },
    "visualContainerObjects": {
      "border": [
        {
          "properties": {
            "show": {
              "expr": {
                "Literal": {
                  "Value": "true"
                }
              }
            },
            "radius": {
              "expr": {
                "Literal": {
                  "Value": "15D"
                }
              }
            },
            "width": {
              "expr": {
                "Literal": {
                  "Value": "1D"
                }
              }
            },
            "color": {
              "solid": {
                "color": {
                  "expr": {
                    "ThemeDataColor": {
                      "ColorId": 2,
                      "Percent": -0.5
                    }
                  }
                }
              }
            }
          }
        }
      ],
      "title": [
        {
          "properties": {
            "text": {
              "expr": {
                "Measure": {
                  "Expression": {
                    "SourceRef": {
                      "Entity": "Medidas_DRE"
                    }
                  },
                  "Property": "TxtDiaAtual"
                }
              }
            },
            "show": {
              "expr": {
                "Literal": {
                  "Value": "true"
                }
              }
            },
            "titleWrap": {
              "expr": {
                "Literal": {
                  "Value": "true"
                }
              }
            },
            "alignment": {
              "expr": {
                "Literal": {
                  "Value": "'center'"
                }
              }
            },
            "bold": {
              "expr": {
                "Literal": {
                  "Value": "false"
                }
              }
            },
            "fontColor": {
              "solid": {
                "color": {
                  "expr": {
                    "ThemeDataColor": {
                      "ColorId": 1,
                      "Percent": 0
                    }
                  }
                }
              }
            }
          }
        }
      ],
      "stylePreset": [
        {
          "properties": {
            "name": {
              "expr": {
                "Literal": {
                  "Value": "'None'"
                }
              }
            }
          }
        }
      ],
      "background": [
        {
          "properties": {
            "show": {
              "expr": {
                "Literal": {
                  "Value": "true"
                }
              }
            },
            "transparency": {
              "expr": {
                "Literal": {
                  "Value": "0D"
                }
              }
            }
          }
        }
      ],
      "padding": [
        {
          "properties": {
            "top": {
              "expr": {
                "Literal": {
                  "Value": "20D"
                }
              }
            },
            "bottom": {
              "expr": {
                "Literal": {
                  "Value": "20D"
                }
              }
            }
          }
        }
      ]
    },
    "drillFilterOtherVisuals": true
  },
  "filterConfig": {
    "filters": [
      {
        "name": "7fa026d89c185421a6d0",
        "field": {
          "Column": {
            "Expression": {
              "SourceRef": {
                "Entity": "D_Calendario"
              }
            },
            "Property": "Mes/Ano"
          }
        },
        "type": "Categorical"
      },
      {
        "name": "422037abd07bb2838541",
        "field": {
          "Column": {
            "Expression": {
              "SourceRef": {
                "Entity": "D_PlanoDeContas"
              }
            },
            "Property": "DRE"
          }
        },
        "type": "Categorical"
      },
      {
        "name": "0f25138ba79dafe2681e",
        "field": {
          "Column": {
            "Expression": {
              "SourceRef": {
                "Entity": "F_Movimentacoes"
              }
            },
            "Property": "Nome_Operacao"
          }
        },
        "type": "Categorical"
      },
      {
        "name": "dc4c4738977f5c381ef3",
        "field": {
          "Column": {
            "Expression": {
              "SourceRef": {
                "Entity": "F_Movimentacoes"
              }
            },
            "Property": "Produto"
          }
        },
        "type": "Categorical"
      },
      {
        "name": "6c3b3ab17c1e2d45b254",
        "field": {
          "Column": {
            "Expression": {
              "SourceRef": {
                "Entity": "D_Calendario"
              }
            },
            "Property": "Date"
          }
        },
        "type": "Categorical"
      },
      {
        "name": "56cc400162e7a8a3bb9f",
        "field": {
          "Measure": {
            "Expression": {
              "SourceRef": {
                "Entity": "Medidas_DRE"
              }
            },
            "Property": "Valor_DRE"
          }
        },
        "type": "Advanced"
      },
      {
        "name": "645a0cd90431342e4b9e",
        "field": {
          "Measure": {
            "Expression": {
              "SourceRef": {
                "Entity": "Medidas_DRE"
              }
            },
            "Property": "% DRE"
          }
        },
        "type": "Advanced"
      }
    ]
  }
}